{
  "score": 102.808746,
  "timeLimit": 0,
  "column": 33,
  "row": 33,
  "listGeckoInMap": [
    {
      "colorGecko": 4,
      "listNode": [
        722,
        721,
        688,
        687,
        654,
        655,
        656,
        623,
        590,
        557,
        556,
        555,
        554,
        587,
        620,
        619,
        586,
        553,
        520,
        519,
        486,
        487,
        488,
        521,
        522,
        489,
        456,
        455,
        422,
        421,
        454,
        453,
        420
      ],
      "indexHead": 722
    },
    {
      "colorGecko": 5,
      "listNode": [
        451,
        450,
        449,
        482,
        481,
        480,
        447,
        448,
        415,
        414,
        413,
        446,
        479,
        512,
        511,
        544,
        577,
        610,
        643,
        642,
        641,
        608,
        575,
        542,
        543,
        510,
        477,
        476,
        475,
        442,
        409,
        408,
        375,
        342,
        309,
        310,
        343,
        376,
        377,
        344,
        311,
        278,
        245
      ],
      "indexHead": 451
    },
    {
      "colorGecko": 0,
      "listNode": [
        765,
        764,
        763,
        762,
        761,
        760,
        759,
        792,
        793,
        826,
        827,
        860,
        861,
        862,
        863,
        830,
        797,
        798,
        799,
        800
      ],
      "indexHead": 765
    },
    {
      "colorGecko": 0,
      "listNode": [
        751,
        784,
        783,
        782,
        749,
        716,
        683,
        650,
        651,
        684,
        717,
        750
      ],
      "indexHead": 751
    },
    {
      "colorGecko": 1,
      "listNode": [
        568,
        535,
        536,
        569,
        602,
        635,
        636,
        637,
        670,
        703,
        702,
        669
      ],
      "indexHead": 568
    },
    {
      "colorGecko": 6,
      "listNode": [
        321,
        322,
        323,
        290,
        257
      ],
      "indexHead": 321
    },
    {
      "colorGecko": 1,
      "listNode": [
        439,
        438,
        405,
        406,
        373,
        374,
        407
      ],
      "indexHead": 439
    },
    {
      "colorGecko": 2,
      "listNode": [
        614,
        581,
        580,
        579,
        578,
        611,
        644,
        677,
        710,
        743,
        744,
        711,
        678,
        679
      ],
      "indexHead": 614
    },
    {
      "colorGecko": 6,
      "listNode": [
        694,
        727,
        728,
        729,
        730,
        731,
        732,
        733,
        766,
        767,
        734,
        701,
        668,
        667,
        700,
        699,
        666,
        633,
        632,
        631,
        664,
        665,
        698,
        697,
        696,
        695
      ],
      "indexHead": 694
    },
    {
      "colorGecko": 4,
      "listNode": [
        402,
        435,
        468,
        467,
        500,
        533,
        534,
        501,
        502,
        503,
        504,
        537,
        538,
        505,
        472,
        473,
        440,
        441
      ],
      "indexHead": 402
    },
    {
      "colorGecko": 1,
      "listNode": [
        353,
        386,
        419,
        452,
        485,
        518,
        551
      ],
      "indexHead": 353
    },
    {
      "colorGecko": 4,
      "listNode": [
        509,
        508,
        541,
        574
      ],
      "indexHead": 509
    },
    {
      "colorGecko": 6,
      "listNode": [
        588,
        589,
        622,
        621
      ],
      "indexHead": 588
    },
    {
      "colorGecko": 1,
      "listNode": [
        758,
        791,
        790,
        757,
        724,
        691,
        658,
        657,
        624,
        591
      ],
      "indexHead": 758
    },
    {
      "colorGecko": 4,
      "listNode": [
        380,
        347,
        314,
        281,
        282,
        283,
        284,
        251,
        250
      ],
      "indexHead": 380
    },
    {
      "colorGecko": 4,
      "listNode": [
        726,
        693,
        660
      ],
      "indexHead": 726
    },
    {
      "colorGecko": 2,
      "listNode": [
        315,
        316,
        317,
        318,
        351,
        350
      ],
      "indexHead": 315
    },
    {
      "colorGecko": 0,
      "listNode": [
        268,
        301,
        334,
        367,
        400,
        401,
        368,
        335
      ],
      "indexHead": 268
    },
    {
      "colorGecko": 4,
      "listNode": [
        248,
        247,
        246
      ],
      "indexHead": 248
    },
    {
      "colorGecko": 5,
      "listNode": [
        652,
        685,
        718
      ],
      "indexHead": 652
    },
    {
      "colorGecko": 0,
      "listNode": [
        615,
        582
      ],
      "indexHead": 615
    },
    {
      "colorGecko": 2,
      "listNode": [
        273,
        274,
        307,
        306,
        339,
        340,
        341,
        308,
        275,
        276,
        277
      ],
      "indexHead": 273
    },
    {
      "colorGecko": 1,
      "listNode": [
        597,
        630,
        663,
        662,
        629,
        628,
        661
      ],
      "indexHead": 597
    },
    {
      "colorGecko": 6,
      "listNode": [
        796,
        795,
        828,
        829
      ],
      "indexHead": 796
    },
    {
      "colorGecko": 5,
      "listNode": [
        612,
        613,
        646,
        645
      ],
      "indexHead": 612
    },
    {
      "colorGecko": 2,
      "listNode": [
        369,
        370,
        371,
        338,
        305,
        272,
        239,
        238,
        271
      ],
      "indexHead": 369
    },
    {
      "colorGecko": 6,
      "listNode": [
        774,
        741,
        708,
        707,
        740,
        773,
        806,
        805,
        838,
        837,
        870
      ],
      "indexHead": 774
    },
    {
      "colorGecko": 6,
      "listNode": [
        595,
        596,
        563,
        564,
        565,
        532,
        499
      ],
      "indexHead": 595
    },
    {
      "colorGecko": 5,
      "listNode": [
        333,
        366,
        365,
        398,
        399,
        432,
        433,
        466
      ],
      "indexHead": 333
    },
    {
      "colorGecko": 5,
      "listNode": [
        403,
        404,
        437,
        470,
        469
      ],
      "indexHead": 403
    },
    {
      "colorGecko": 4,
      "listNode": [
        243,
        242,
        241,
        240,
        207,
        206,
        205,
        204
      ],
      "indexHead": 243
    },
    {
      "colorGecko": 0,
      "listNode": [
        570,
        603,
        604,
        571,
        572,
        573,
        540,
        539,
        506,
        507,
        474
      ],
      "indexHead": 570
    },
    {
      "colorGecko": 3,
      "listNode": [
        416,
        383,
        382,
        381,
        348,
        349
      ],
      "indexHead": 416
    },
    {
      "colorGecko": 3,
      "listNode": [
        325,
        358,
        391,
        424,
        423,
        390,
        389,
        388,
        387,
        354,
        355,
        356,
        357,
        324,
        291
      ],
      "indexHead": 325
    },
    {
      "colorGecko": 3,
      "listNode": [
        222,
        255,
        256,
        289,
        288,
        287,
        286,
        253,
        252,
        219,
        220,
        221,
        254
      ],
      "indexHead": 222
    },
    {
      "colorGecko": 6,
      "listNode": [
        445,
        412,
        379,
        346,
        313,
        280,
        279,
        312,
        345,
        378,
        411,
        444
      ],
      "indexHead": 445
    },
    {
      "colorGecko": 6,
      "listNode": [
        690,
        689
      ],
      "indexHead": 690
    },
    {
      "colorGecko": 1,
      "listNode": [
        653,
        686,
        719,
        752,
        785,
        818,
        851,
        852,
        885,
        886,
        887,
        854,
        855
      ],
      "indexHead": 653
    },
    {
      "colorGecko": 4,
      "listNode": [
        850,
        817,
        816
      ],
      "indexHead": 850
    },
    {
      "colorGecko": 6,
      "listNode": [
        236,
        237,
        270,
        269,
        302,
        303,
        304,
        337,
        336
      ],
      "indexHead": 236
    },
    {
      "colorGecko": 6,
      "listNode": [
        748,
        715,
        714,
        713,
        680,
        681,
        682,
        649,
        648,
        647
      ],
      "indexHead": 748
    },
    {
      "colorGecko": 6,
      "listNode": [
        768,
        735,
        736,
        737,
        704,
        671,
        672,
        639,
        638,
        605,
        606,
        607,
        640,
        673,
        674,
        675,
        676,
        709,
        742,
        775,
        808,
        809,
        842,
        843,
        844,
        877
      ],
      "indexHead": 768
    },
    {
      "colorGecko": 6,
      "listNode": [
        823,
        822,
        789,
        756,
        755,
        754,
        787,
        788,
        821,
        820,
        819,
        786,
        753,
        720
      ],
      "indexHead": 823
    },
    {
      "colorGecko": 3,
      "listNode": [
        484,
        483,
        516,
        515,
        514,
        513,
        546,
        547,
        548,
        549,
        550,
        583,
        584,
        617,
        618,
        585,
        552
      ],
      "indexHead": 484
    },
    {
      "colorGecko": 0,
      "listNode": [
        319,
        352,
        385,
        418,
        417,
        384
      ],
      "indexHead": 319
    },
    {
      "colorGecko": 3,
      "listNode": [
        598,
        599,
        566,
        567,
        600,
        601,
        634
      ],
      "indexHead": 598
    }
  ],
  "listBrickInMap": [],
  "listExitsInMap": [],
  "listStopInMap": [],
  "listBarrierInMap": []
}