{
  "column": 19,
  "row": 23,
  "listGeckoInMap": [
    {
      "colorGecko": 5,
      "listNode": [
        265,
        264
      ],
      "indexHead": 265
    },
    {
      "colorGecko": 3,
      "listNode": [
        436,
        417,
        398
      ],
      "indexHead": 436
    },
    {
      "colorGecko": 5,
      "listNode": [
        435,
        434,
        415
      ],
      "indexHead": 435
    },
    {
      "colorGecko": 4,
      "listNode": [
        416,
        397,
        396,
        377,
        358,
        357,
        356
      ],
      "indexHead": 416
    },
    {
      "colorGecko": 2,
      "listNode": [
        150,
        149,
        130,
        129,
        110,
        91,
        92,
        111,
        112,
        131,
        132,
        113,
        94,
        75,
        56,
        55,
        54,
        35,
        34,
        15,
        16,
        17,
        18,
        37,
        36
      ],
      "indexHead": 150
    },
    {
      "colorGecko": 5,
      "listNode": [
        14,
        13,
        32,
        33
      ],
      "indexHead": 14
    },
    {
      "colorGecko": 4,
      "listNode": [
        31,
        30,
        29,
        28,
        9,
        8,
        27,
        46,
        45,
        26,
        25,
        6,
        5,
        4,
        3,
        22,
        21,
        2,
        1,
        20,
        19,
        38,
        39,
        58,
        57,
        76,
        77,
        96,
        115,
        116,
        97
      ],
      "indexHead": 31
    },
    {
      "colorGecko": 3,
      "listNode": [
        12,
        11,
        10
      ],
      "indexHead": 12
    },
    {
      "colorGecko": 2,
      "listNode": [
        47,
        66,
        85,
        104,
        123,
        142,
        161,
        180,
        199,
        218,
        237,
        256,
        275,
        294,
        295,
        296,
        297,
        298,
        317,
        336,
        355,
        374,
        393,
        392,
        391,
        390,
        389,
        388,
        387,
        386,
        385,
        384,
        383,
        382,
        381,
        380,
        361,
        342,
        323,
        304,
        285,
        266,
        247,
        228,
        209,
        190,
        171,
        152
      ],
      "indexHead": 47
    },
    {
      "colorGecko": 2,
      "listNode": [
        65,
        84,
        103,
        122,
        121,
        102,
        101,
        120,
        139,
        140,
        141
      ],
      "indexHead": 65
    },
    {
      "colorGecko": 5,
      "listNode": [
        23,
        24,
        43,
        42,
        61,
        60,
        59,
        40,
        41
      ],
      "indexHead": 23
    },
    {
      "colorGecko": 6,
      "listNode": [
        62,
        63,
        44
      ],
      "indexHead": 62
    },
    {
      "colorGecko": 1,
      "listNode": [
        81,
        100,
        119,
        138
      ],
      "indexHead": 81
    },
    {
      "colorGecko": 1,
      "listNode": [
        48,
        49,
        50,
        69,
        88,
        89,
        108,
        109,
        90,
        71
      ],
      "indexHead": 48
    },
    {
      "colorGecko": 6,
      "listNode": [
        67,
        68,
        87
      ],
      "indexHead": 67
    },
    {
      "colorGecko": 1,
      "listNode": [
        86,
        105,
        106,
        125,
        126,
        107
      ],
      "indexHead": 86
    },
    {
      "colorGecko": 1,
      "listNode": [
        51,
        70
      ],
      "indexHead": 51
    },
    {
      "colorGecko": 0,
      "listNode": [
        127,
        146,
        145,
        164,
        165,
        166,
        147,
        128
      ],
      "indexHead": 127
    },
    {
      "colorGecko": 1,
      "listNode": [
        72,
        73,
        74,
        93
      ],
      "indexHead": 72
    },
    {
      "colorGecko": 6,
      "listNode": [
        52,
        53
      ],
      "indexHead": 52
    },
    {
      "colorGecko": 1,
      "listNode": [
        148,
        167,
        168
      ],
      "indexHead": 148
    },
    {
      "colorGecko": 5,
      "listNode": [
        144,
        143,
        162,
        163,
        182,
        181,
        200,
        201,
        202
      ],
      "indexHead": 144
    },
    {
      "colorGecko": 6,
      "listNode": [
        238,
        257,
        258,
        259,
        260,
        241,
        242,
        261,
        262,
        263,
        282,
        283,
        284,
        303,
        322,
        321,
        340,
        339,
        338,
        319,
        320,
        301,
        300,
        281,
        280,
        299,
        318,
        337
      ],
      "indexHead": 238
    },
    {
      "colorGecko": 0,
      "listNode": [
        244,
        225,
        226,
        245,
        246,
        227,
        208,
        207,
        188,
        169,
        170,
        189
      ],
      "indexHead": 244
    },
    {
      "colorGecko": 4,
      "listNode": [
        206,
        187,
        186,
        185,
        184,
        183
      ],
      "indexHead": 206
    },
    {
      "colorGecko": 1,
      "listNode": [
        360,
        379,
        378,
        359
      ],
      "indexHead": 360
    },
    {
      "colorGecko": 4,
      "listNode": [
        240,
        239,
        220,
        221,
        222,
        203,
        204,
        205,
        224,
        223
      ],
      "indexHead": 240
    },
    {
      "colorGecko": 0,
      "listNode": [
        254,
        253,
        234
      ],
      "indexHead": 254
    },
    {
      "colorGecko": 1,
      "listNode": [
        375,
        394,
        395,
        376
      ],
      "indexHead": 375
    },
    {
      "colorGecko": 5,
      "listNode": [
        414,
        433
      ],
      "indexHead": 414
    },
    {
      "colorGecko": 2,
      "listNode": [
        432,
        431,
        412,
        411,
        430,
        429,
        410,
        409
      ],
      "indexHead": 432
    },
    {
      "colorGecko": 4,
      "listNode": [
        428,
        427,
        426,
        425,
        424,
        423,
        422,
        421,
        420
      ],
      "indexHead": 428
    },
    {
      "colorGecko": 1,
      "listNode": [
        407,
        406,
        405,
        404,
        403,
        402,
        401,
        400,
        419,
        418,
        399
      ],
      "indexHead": 407
    },
    {
      "colorGecko": 4,
      "listNode": [
        373,
        354,
        335,
        316,
        315
      ],
      "indexHead": 373
    },
    {
      "colorGecko": 4,
      "listNode": [
        314,
        313
      ],
      "indexHead": 314
    },
    {
      "colorGecko": 2,
      "listNode": [
        368,
        349,
        330,
        311,
        292,
        293,
        312,
        331
      ],
      "indexHead": 368
    },
    {
      "colorGecko": 2,
      "listNode": [
        235,
        216,
        217,
        198,
        179,
        178,
        159,
        158,
        177,
        176,
        157
      ],
      "indexHead": 235
    },
    {
      "colorGecko": 0,
      "listNode": [
        195,
        214,
        215,
        196,
        197
      ],
      "indexHead": 195
    },
    {
      "colorGecko": 5,
      "listNode": [
        233,
        252,
        271,
        270,
        251,
        232,
        231,
        212,
        213,
        194,
        193,
        174,
        175,
        156,
        137,
        118,
        117,
        98,
        99,
        80,
        79,
        78
      ],
      "indexHead": 233
    },
    {
      "colorGecko": 1,
      "listNode": [
        82,
        83
      ],
      "indexHead": 82
    },
    {
      "colorGecko": 6,
      "listNode": [
        136,
        155,
        154,
        153,
        172,
        173,
        192,
        191,
        210,
        211,
        230,
        229,
        248,
        249,
        250,
        269,
        268,
        287,
        286,
        305,
        306,
        325,
        344,
        363,
        364,
        345,
        346
      ],
      "indexHead": 136
    },
    {
      "colorGecko": 0,
      "listNode": [
        135,
        134,
        133,
        114,
        95
      ],
      "indexHead": 135
    },
    {
      "colorGecko": 4,
      "listNode": [
        288,
        307,
        308,
        327,
        328,
        329,
        310,
        291,
        290,
        309
      ],
      "indexHead": 288
    },
    {
      "colorGecko": 4,
      "listNode": [
        276,
        277,
        278,
        279
      ],
      "indexHead": 276
    },
    {
      "colorGecko": 0,
      "listNode": [
        334,
        353,
        372,
        371,
        352,
        333,
        332,
        351,
        350,
        369,
        370
      ],
      "indexHead": 334
    },
    {
      "colorGecko": 6,
      "listNode": [
        348,
        347
      ],
      "indexHead": 348
    },
    {
      "colorGecko": 0,
      "listNode": [
        343,
        362
      ],
      "indexHead": 343
    },
    {
      "colorGecko": 4,
      "listNode": [
        367,
        366,
        365
      ],
      "indexHead": 367
    }
  ],
  "listBrickInMap": [],
  "listExitsInMap": [],
  "listStopInMap": [],
  "listBarrierInMap": []
}