{
  "column": 21,
  "row": 22,
  "listGeckoInMap": [
    {
      "colorGecko": 4,
      "listNode": [
        125,
        124
      ],
      "indexHead": 125
    },
    {
      "colorGecko": 4,
      "listNode": [
        20,
        41,
        62,
        83,
        104,
        103,
        102,
        81,
        60,
        39,
        18,
        19,
        40,
        61,
        82
      ],
      "indexHead": 20
    },
    {
      "colorGecko": 1,
      "listNode": [
        168,
        169
      ],
      "indexHead": 168
    },
    {
      "colorGecko": 4,
      "listNode": [
        461,
        460,
        459,
        458
      ],
      "indexHead": 461
    },
    {
      "colorGecko": 3,
      "listNode": [
        84,
        85,
        86,
        87,
        88,
        109,
        110,
        111,
        112
      ],
      "indexHead": 84
    },
    {
      "colorGecko": 2,
      "listNode": [
        89,
        90
      ],
      "indexHead": 89
    },
    {
      "colorGecko": 5,
      "listNode": [
        438,
        417
      ],
      "indexHead": 438
    },
    {
      "colorGecko": 6,
      "listNode": [
        447,
        426,
        405,
        384,
        363,
        362,
        383,
        404,
        425,
        424,
        445,
        446
      ],
      "indexHead": 447
    },
    {
      "colorGecko": 6,
      "listNode": [
        423,
        402,
        403,
        382,
        361,
        360,
        381,
        380,
        401,
        422,
        443
      ],
      "indexHead": 423
    },
    {
      "colorGecko": 3,
      "listNode": [
        12,
        33,
        34,
        55
      ],
      "indexHead": 12
    },
    {
      "colorGecko": 6,
      "listNode": [
        76,
        97,
        98,
        77,
        56,
        35,
        14,
        15,
        16,
        37,
        38,
        59,
        80,
        101,
        122,
        123,
        144,
        145,
        146,
        167,
        166,
        187,
        186,
        185,
        184,
        205,
        204,
        203,
        224,
        225,
        226,
        227,
        248,
        247,
        268,
        267,
        288,
        309
      ],
      "indexHead": 76
    },
    {
      "colorGecko": 6,
      "listNode": [
        165,
        164,
        163,
        162,
        141
      ],
      "indexHead": 165
    },
    {
      "colorGecko": 2,
      "listNode": [
        79,
        100,
        121,
        120,
        119
      ],
      "indexHead": 79
    },
    {
      "colorGecko": 0,
      "listNode": [
        140,
        161,
        160,
        159,
        158,
        137,
        136,
        115,
        116,
        117,
        118,
        139,
        138
      ],
      "indexHead": 140
    },
    {
      "colorGecko": 0,
      "listNode": [
        157,
        156,
        135,
        134,
        133,
        132,
        131,
        152,
        173,
        174,
        195,
        196,
        175,
        154,
        153
      ],
      "indexHead": 157
    },
    {
      "colorGecko": 6,
      "listNode": [
        114,
        113,
        92,
        91,
        70,
        69,
        68,
        67,
        66,
        45,
        44,
        23,
        24,
        25,
        46,
        47,
        26,
        5,
        4,
        3
      ],
      "indexHead": 114
    },
    {
      "colorGecko": 3,
      "listNode": [
        94,
        95,
        96,
        75,
        54,
        53,
        52,
        73,
        74
      ],
      "indexHead": 94
    },
    {
      "colorGecko": 5,
      "listNode": [
        108,
        107,
        106,
        105,
        126,
        147,
        148,
        127,
        128,
        129,
        130,
        151,
        172,
        193,
        214,
        235,
        234,
        213,
        192,
        191,
        212,
        233,
        254,
        255,
        256,
        257,
        258,
        279,
        300,
        299,
        298,
        319,
        318,
        297
      ],
      "indexHead": 108
    },
    {
      "colorGecko": 5,
      "listNode": [
        150,
        171,
        170,
        149
      ],
      "indexHead": 150
    },
    {
      "colorGecko": 2,
      "listNode": [
        142,
        143
      ],
      "indexHead": 142
    },
    {
      "colorGecko": 3,
      "listNode": [
        290,
        311,
        312,
        313,
        292,
        271,
        272,
        251,
        250,
        249,
        270,
        291
      ],
      "indexHead": 290
    },
    {
      "colorGecko": 5,
      "listNode": [
        176,
        177,
        178,
        179,
        180,
        181,
        182,
        183
      ],
      "indexHead": 176
    },
    {
      "colorGecko": 4,
      "listNode": [
        202,
        223,
        222,
        221,
        200,
        199,
        198,
        197,
        218,
        239,
        238,
        237,
        236,
        215,
        216
      ],
      "indexHead": 202
    },
    {
      "colorGecko": 2,
      "listNode": [
        310,
        331,
        352,
        373,
        374,
        395,
        396,
        375,
        354,
        333,
        332,
        353
      ],
      "indexHead": 310
    },
    {
      "colorGecko": 6,
      "listNode": [
        228,
        207,
        208,
        229,
        230,
        209,
        188
      ],
      "indexHead": 228
    },
    {
      "colorGecko": 1,
      "listNode": [
        334,
        355,
        376,
        397,
        418,
        439,
        440,
        419,
        398,
        377,
        356,
        335,
        314,
        293
      ],
      "indexHead": 334
    },
    {
      "colorGecko": 4,
      "listNode": [
        220,
        219,
        240,
        261,
        262,
        241,
        242,
        243,
        264,
        263,
        284,
        305,
        304,
        283,
        282,
        303,
        302,
        301,
        280,
        259,
        260,
        281
      ],
      "indexHead": 220
    },
    {
      "colorGecko": 5,
      "listNode": [
        285,
        306,
        327,
        348,
        347,
        346,
        345,
        366,
        367,
        368,
        369,
        370,
        349,
        328,
        307,
        286,
        287,
        266,
        265,
        244,
        245,
        246
      ],
      "indexHead": 285
    },
    {
      "colorGecko": 6,
      "listNode": [
        277,
        276,
        275,
        296,
        317,
        338,
        339,
        340,
        341,
        320,
        321,
        322
      ],
      "indexHead": 277
    },
    {
      "colorGecko": 5,
      "listNode": [
        48,
        27,
        6,
        7
      ],
      "indexHead": 48
    },
    {
      "colorGecko": 3,
      "listNode": [
        28,
        49,
        50,
        71,
        72,
        51,
        30,
        9,
        8,
        29
      ],
      "indexHead": 28
    },
    {
      "colorGecko": 4,
      "listNode": [
        323,
        344,
        343,
        364,
        365,
        386,
        407,
        428,
        429,
        430
      ],
      "indexHead": 323
    },
    {
      "colorGecko": 2,
      "listNode": [
        406,
        427,
        448,
        449,
        450,
        451,
        452,
        453,
        454,
        455,
        456,
        457,
        436,
        437,
        416,
        415,
        414,
        435,
        434,
        433,
        432,
        411,
        410,
        389,
        388,
        409,
        408,
        387
      ],
      "indexHead": 406
    },
    {
      "colorGecko": 6,
      "listNode": [
        393,
        372,
        371,
        392,
        391,
        412,
        413
      ],
      "indexHead": 393
    },
    {
      "colorGecko": 1,
      "listNode": [
        351,
        330,
        329,
        350
      ],
      "indexHead": 351
    },
    {
      "colorGecko": 3,
      "listNode": [
        99,
        78,
        57,
        36
      ],
      "indexHead": 99
    },
    {
      "colorGecko": 2,
      "listNode": [
        65,
        64,
        63
      ],
      "indexHead": 65
    },
    {
      "colorGecko": 6,
      "listNode": [
        326,
        325,
        324
      ],
      "indexHead": 326
    },
    {
      "colorGecko": 4,
      "listNode": [
        31,
        10,
        11,
        32
      ],
      "indexHead": 31
    },
    {
      "colorGecko": 4,
      "listNode": [
        2,
        1,
        22,
        43,
        42,
        21,
        0
      ],
      "indexHead": 2
    },
    {
      "colorGecko": 5,
      "listNode": [
        190,
        211,
        232,
        253,
        274,
        295,
        316,
        337,
        358,
        379,
        400,
        421,
        442,
        441,
        420,
        399,
        378,
        357,
        336,
        315,
        294,
        273,
        252,
        231,
        210,
        189
      ],
      "indexHead": 190
    }
  ],
  "listBrickInMap": [],
  "listExitsInMap": [],
  "listStopInMap": [],
  "listBarrierInMap": []
}