{
  "column": 18,
  "row": 27,
  "listGeckoInMap": [
    {
      "colorGecko": 3,
      "listNode": [
        147,
        165,
        183,
        201
      ],
      "indexHead": 147
    },
    {
      "colorGecko": 0,
      "listNode": [
        374,
        373,
        372,
        371,
        370,
        369,
        351,
        333,
        334,
        335,
        336,
        337,
        338,
        320,
        302
      ],
      "indexHead": 374
    },
    {
      "colorGecko": 2,
      "listNode": [
        249,
        267,
        285,
        303,
        321
      ],
      "indexHead": 249
    },
    {
      "colorGecko": 6,
      "listNode": [
        59,
        60
      ],
      "indexHead": 59
    },
    {
      "colorGecko": 5,
      "listNode": [
        361,
        343,
        325,
        307,
        289,
        271,
        253,
        235,
        217,
        199,
        181
      ],
      "indexHead": 361
    },
    {
      "colorGecko": 4,
      "listNode": [
        164,
        182,
        200,
        218,
        219,
        237,
        255,
        273,
        291,
        309,
        327,
        345
      ],
      "indexHead": 164
    },
    {
      "colorGecko": 5,
      "listNode": [
        103,
        102,
        101,
        83,
        84,
        85
      ],
      "indexHead": 103
    },
    {
      "colorGecko": 0,
      "listNode": [
        363,
        381,
        399,
        417,
        416,
        398,
        380,
        362,
        344,
        326,
        308,
        290,
        272,
        254,
        236
      ],
      "indexHead": 363
    },
    {
      "colorGecko": 0,
      "listNode": [
        368,
        367,
        385,
        403,
        421,
        422,
        423,
        424,
        425,
        426,
        427,
        428,
        410,
        392,
        391,
        390,
        389,
        388
      ],
      "indexHead": 368
    },
    {
      "colorGecko": 2,
      "listNode": [
        67,
        66,
        65,
        47,
        46,
        45,
        44,
        62,
        80,
        79,
        78,
        77,
        76,
        94
      ],
      "indexHead": 67
    },
    {
      "colorGecko": 6,
      "listNode": [
        446,
        445,
        444,
        443,
        442,
        441,
        440,
        439,
        438,
        420,
        402,
        384,
        366,
        348,
        330
      ],
      "indexHead": 446
    },
    {
      "colorGecko": 1,
      "listNode": [
        112,
        130,
        148,
        166,
        184,
        202,
        220,
        238,
        256,
        274,
        292,
        310,
        328,
        346,
        364,
        382,
        400
      ],
      "indexHead": 112
    },
    {
      "colorGecko": 0,
      "listNode": [
        404,
        386,
        387,
        405,
        406,
        407,
        408,
        409
      ],
      "indexHead": 404
    },
    {
      "colorGecko": 3,
      "listNode": [
        350,
        332,
        331,
        349
      ],
      "indexHead": 350
    },
    {
      "colorGecko": 1,
      "listNode": [
        137,
        155,
        173,
        191,
        209,
        227,
        245,
        263,
        281,
        282,
        300,
        318,
        319,
        301
      ],
      "indexHead": 137
    },
    {
      "colorGecko": 5,
      "listNode": [
        299,
        317,
        316,
        315,
        314,
        313,
        312,
        311,
        329,
        347,
        365,
        383,
        401,
        419,
        437,
        436,
        435
      ],
      "indexHead": 299
    },
    {
      "colorGecko": 4,
      "listNode": [
        298,
        297,
        296,
        295,
        294,
        293,
        275,
        257,
        239,
        221,
        203,
        185,
        167,
        149,
        131,
        113,
        95,
        96,
        97,
        98,
        99,
        100,
        82,
        64
      ],
      "indexHead": 298
    },
    {
      "colorGecko": 2,
      "listNode": [
        277,
        278,
        279,
        280,
        262,
        244,
        243
      ],
      "indexHead": 277
    },
    {
      "colorGecko": 1,
      "listNode": [
        258,
        259,
        260,
        261
      ],
      "indexHead": 258
    },
    {
      "colorGecko": 5,
      "listNode": [
        353,
        354,
        355,
        356
      ],
      "indexHead": 353
    },
    {
      "colorGecko": 0,
      "listNode": [
        264,
        246,
        228,
        210,
        192,
        174,
        156,
        138,
        120,
        121,
        139,
        157,
        175,
        176,
        194,
        212,
        230,
        248,
        266,
        284,
        283,
        265,
        247,
        229,
        211,
        193
      ],
      "indexHead": 264
    },
    {
      "colorGecko": 0,
      "listNode": [
        241,
        240,
        222,
        204,
        186,
        168,
        150,
        132,
        114,
        115,
        116
      ],
      "indexHead": 241
    },
    {
      "colorGecko": 6,
      "listNode": [
        117,
        118
      ],
      "indexHead": 117
    },
    {
      "colorGecko": 2,
      "listNode": [
        133,
        151
      ],
      "indexHead": 133
    },
    {
      "colorGecko": 0,
      "listNode": [
        135,
        136,
        154,
        172,
        190,
        208,
        226,
        225,
        224,
        223,
        205,
        206,
        207,
        189,
        171,
        153,
        152,
        170,
        188,
        187,
        169
      ],
      "indexHead": 135
    },
    {
      "colorGecko": 2,
      "listNode": [
        81,
        63
      ],
      "indexHead": 81
    }
  ],
  "listBrickInMap": [],
  "listExitsInMap": [],
  "listStopInMap": [],
  "listBarrierInMap": []
}