{
  "column": 20,
  "row": 25,
  "listGeckoInMap": [
    {
      "colorGecko": 6,
      "listNode": [
        25,
        45,
        46
      ],
      "indexHead": 25
    },
    {
      "colorGecko": 6,
      "listNode": [
        453,
        452,
        451,
        450,
        449,
        448,
        447,
        446
      ],
      "indexHead": 453
    },
    {
      "colorGecko": 4,
      "listNode": [
        71,
        91,
        92,
        93,
        94,
        95,
        75,
        74,
        73,
        72,
        52
      ],
      "indexHead": 71
    },
    {
      "colorGecko": 5,
      "listNode": [
        65,
        85,
        105,
        104,
        103,
        83,
        63,
        64,
        84
      ],
      "indexHead": 65
    },
    {
      "colorGecko": 2,
      "listNode": [
        403,
        404,
        424,
        444,
        464
      ],
      "indexHead": 403
    },
    {
      "colorGecko": 0,
      "listNode": [
        282,
        283,
        284,
        285,
        286,
        266,
        267,
        268,
        288,
        308,
        307,
        306,
        305,
        304
      ],
      "indexHead": 282
    },
    {
      "colorGecko": 0,
      "listNode": [
        43,
        42,
        62,
        82,
        102,
        122,
        123,
        124,
        125,
        145,
        165,
        166,
        167,
        168,
        148,
        128
      ],
      "indexHead": 43
    },
    {
      "colorGecko": 4,
      "listNode": [
        144,
        164
      ],
      "indexHead": 144
    },
    {
      "colorGecko": 0,
      "listNode": [
        115,
        114,
        113,
        112,
        111,
        110,
        130,
        150,
        170,
        190,
        210,
        230,
        250,
        270,
        269,
        249,
        229,
        209,
        189,
        188,
        187,
        186,
        185,
        184,
        204,
        224,
        244,
        245,
        246,
        247,
        248,
        228,
        208,
        207,
        206,
        205,
        225,
        226,
        227
      ],
      "indexHead": 115
    },
    {
      "colorGecko": 6,
      "listNode": [
        290,
        310,
        330,
        329,
        328
      ],
      "indexHead": 290
    },
    {
      "colorGecko": 0,
      "listNode": [
        131,
        151,
        171,
        191,
        211,
        231,
        232,
        233,
        234,
        254,
        274,
        294,
        314,
        334,
        335,
        336,
        316,
        315,
        295,
        275,
        255,
        235,
        215,
        195,
        175,
        155,
        135,
        136,
        137,
        157,
        177,
        197,
        217,
        237,
        257,
        277,
        297,
        317,
        337,
        357,
        377
      ],
      "indexHead": 131
    },
    {
      "colorGecko": 4,
      "listNode": [
        133,
        132
      ],
      "indexHead": 133
    },
    {
      "colorGecko": 0,
      "listNode": [
        176,
        196,
        216,
        236,
        256,
        276,
        296
      ],
      "indexHead": 176
    },
    {
      "colorGecko": 4,
      "listNode": [
        271,
        291,
        311,
        331,
        351,
        371,
        370,
        369,
        368,
        367,
        366,
        386,
        406,
        407,
        408,
        409,
        389,
        388,
        387
      ],
      "indexHead": 271
    },
    {
      "colorGecko": 3,
      "listNode": [
        273,
        272,
        252,
        253
      ],
      "indexHead": 273
    },
    {
      "colorGecko": 4,
      "listNode": [
        265,
        264,
        263,
        243,
        223,
        203,
        183,
        163,
        143,
        142,
        141,
        161,
        181,
        201,
        221,
        241,
        261
      ],
      "indexHead": 265
    },
    {
      "colorGecko": 2,
      "listNode": [
        405,
        425,
        426,
        427,
        428,
        429,
        430,
        431,
        432,
        433,
        434
      ],
      "indexHead": 405
    },
    {
      "colorGecko": 4,
      "listNode": [
        410,
        390,
        391,
        411,
        412,
        413
      ],
      "indexHead": 410
    },
    {
      "colorGecko": 1,
      "listNode": [
        423,
        422
      ],
      "indexHead": 423
    },
    {
      "colorGecko": 1,
      "listNode": [
        194,
        174,
        154,
        153,
        152,
        172,
        192,
        212,
        213,
        193,
        173
      ],
      "indexHead": 194
    },
    {
      "colorGecko": 4,
      "listNode": [
        292,
        312,
        332,
        352,
        353,
        373,
        393,
        392,
        372
      ],
      "indexHead": 292
    },
    {
      "colorGecko": 0,
      "listNode": [
        293,
        313,
        333
      ],
      "indexHead": 293
    },
    {
      "colorGecko": 4,
      "listNode": [
        327,
        326,
        346,
        347,
        348,
        349,
        350
      ],
      "indexHead": 327
    },
    {
      "colorGecko": 4,
      "listNode": [
        262,
        242,
        222,
        202,
        182,
        162
      ],
      "indexHead": 262
    },
    {
      "colorGecko": 0,
      "listNode": [
        309,
        289
      ],
      "indexHead": 309
    },
    {
      "colorGecko": 2,
      "listNode": [
        169,
        149,
        129
      ],
      "indexHead": 169
    },
    {
      "colorGecko": 6,
      "listNode": [
        127,
        126,
        146,
        147
      ],
      "indexHead": 127
    },
    {
      "colorGecko": 1,
      "listNode": [
        106,
        86,
        66,
        67,
        87,
        107,
        108
      ],
      "indexHead": 106
    }
  ],
  "listBrickInMap": [],
  "listExitsInMap": [],
  "listStopInMap": [],
  "listBarrierInMap": []
}