{
  "score": 90.20948,
  "timeLimit": 0,
  "column": 23,
  "row": 28,
  "listGeckoInMap": [
    {
      "colorGecko": 3,
      "listNode": [
        89,
        112
      ],
      "indexHead": 89
    },
    {
      "colorGecko": 3,
      "listNode": [
        345,
        322
      ],
      "indexHead": 345
    },
    {
      "colorGecko": 4,
      "listNode": [
        480,
        479,
        478,
        477,
        500,
        501,
        524,
        525,
        502,
        503
      ],
      "indexHead": 480
    },
    {
      "colorGecko": 3,
      "listNode": [
        136,
        159,
        182,
        205,
        228,
        227,
        226,
        249,
        248,
        225,
        202,
        179,
        180,
        157,
        158,
        135,
        134,
        111,
        110,
        109,
        86,
        85,
        62,
        61,
        84,
        83,
        106,
        107,
        130,
        129,
        152,
        175,
        176,
        153,
        154,
        177,
        178,
        155,
        132,
        131,
        108
      ],
      "indexHead": 136
    },
    {
      "colorGecko": 6,
      "listNode": [
        232,
        255,
        256
      ],
      "indexHead": 232
    },
    {
      "colorGecko": 2,
      "listNode": [
        343,
        342,
        365,
        366,
        389,
        388,
        387,
        386,
        409
      ],
      "indexHead": 343
    },
    {
      "colorGecko": 5,
      "listNode": [
        390,
        413
      ],
      "indexHead": 390
    },
    {
      "colorGecko": 0,
      "listNode": [
        52,
        75,
        74
      ],
      "indexHead": 52
    },
    {
      "colorGecko": 1,
      "listNode": [
        54,
        55,
        56
      ],
      "indexHead": 54
    },
    {
      "colorGecko": 5,
      "listNode": [
        233,
        234
      ],
      "indexHead": 233
    },
    {
      "colorGecko": 4,
      "listNode": [
        415,
        392,
        369,
        346,
        347,
        370,
        393,
        416,
        417,
        440,
        441,
        464
      ],
      "indexHead": 415
    },
    {
      "colorGecko": 2,
      "listNode": [
        254,
        277,
        300,
        323,
        324,
        301,
        278,
        279,
        280,
        257,
        258,
        235,
        236,
        259,
        260,
        283,
        282,
        305,
        304,
        327,
        326,
        349,
        348,
        325,
        302,
        303
      ],
      "indexHead": 254
    },
    {
      "colorGecko": 5,
      "listNode": [
        454,
        431,
        432,
        433,
        410,
        411,
        412,
        435,
        434
      ],
      "indexHead": 454
    },
    {
      "colorGecko": 6,
      "listNode": [
        237,
        238,
        215,
        214,
        213,
        212,
        211,
        210
      ],
      "indexHead": 237
    },
    {
      "colorGecko": 6,
      "listNode": [
        97,
        98,
        121,
        144,
        145,
        168,
        191,
        190,
        167,
        166,
        189,
        188,
        187,
        164,
        141,
        142,
        165
      ],
      "indexHead": 97
    },
    {
      "colorGecko": 4,
      "listNode": [
        192,
        193,
        170,
        171,
        148,
        125,
        126,
        149,
        150,
        127,
        128,
        105,
        82,
        59,
        60
      ],
      "indexHead": 192
    },
    {
      "colorGecko": 5,
      "listNode": [
        151,
        174
      ],
      "indexHead": 151
    },
    {
      "colorGecko": 6,
      "listNode": [
        200,
        223,
        222,
        199,
        198,
        197,
        220,
        221,
        244,
        267,
        266,
        243,
        242,
        241,
        240,
        263,
        262,
        239,
        216,
        217,
        194,
        195,
        218,
        219,
        196,
        173,
        172
      ],
      "indexHead": 200
    },
    {
      "colorGecko": 3,
      "listNode": [
        63,
        64,
        87,
        88,
        65
      ],
      "indexHead": 63
    },
    {
      "colorGecko": 5,
      "listNode": [
        201,
        224
      ],
      "indexHead": 201
    },
    {
      "colorGecko": 1,
      "listNode": [
        203,
        204,
        181
      ],
      "indexHead": 203
    },
    {
      "colorGecko": 5,
      "listNode": [
        250,
        273,
        272,
        271,
        294,
        295,
        318,
        319,
        296
      ],
      "indexHead": 250
    },
    {
      "colorGecko": 0,
      "listNode": [
        341,
        364,
        363,
        340,
        317,
        316,
        315,
        292,
        291,
        268,
        269,
        270,
        247,
        246,
        245
      ],
      "indexHead": 341
    },
    {
      "colorGecko": 3,
      "listNode": [
        314,
        337,
        338,
        339,
        362
      ],
      "indexHead": 314
    },
    {
      "colorGecko": 2,
      "listNode": [
        336,
        335,
        358,
        357,
        334,
        333,
        332,
        309,
        310,
        311,
        288,
        289,
        312,
        313,
        290
      ],
      "indexHead": 336
    },
    {
      "colorGecko": 3,
      "listNode": [
        104,
        103,
        102
      ],
      "indexHead": 104
    },
    {
      "colorGecko": 0,
      "listNode": [
        133,
        156
      ],
      "indexHead": 133
    },
    {
      "colorGecko": 1,
      "listNode": [
        81,
        80,
        79,
        78,
        101,
        124,
        123,
        100,
        99,
        76,
        77
      ],
      "indexHead": 81
    },
    {
      "colorGecko": 5,
      "listNode": [
        120,
        119
      ],
      "indexHead": 120
    },
    {
      "colorGecko": 6,
      "listNode": [
        147,
        146,
        169
      ],
      "indexHead": 147
    },
    {
      "colorGecko": 6,
      "listNode": [
        285,
        308,
        331,
        354,
        355,
        378,
        379,
        402,
        401,
        424,
        447,
        448,
        425,
        426,
        403,
        404,
        427,
        450,
        451,
        428,
        405,
        406,
        429,
        430,
        407,
        408,
        385,
        384,
        361,
        360,
        359,
        382,
        383
      ],
      "indexHead": 285
    },
    {
      "colorGecko": 2,
      "listNode": [
        381,
        380
      ],
      "indexHead": 381
    },
    {
      "colorGecko": 4,
      "listNode": [
        376,
        375
      ],
      "indexHead": 376
    },
    {
      "colorGecko": 6,
      "listNode": [
        473,
        496,
        495,
        518,
        541,
        542,
        565,
        564,
        587,
        588
      ],
      "indexHead": 473
    },
    {
      "colorGecko": 5,
      "listNode": [
        307,
        306
      ],
      "indexHead": 307
    },
    {
      "colorGecko": 1,
      "listNode": [
        261,
        284
      ],
      "indexHead": 261
    },
    {
      "colorGecko": 2,
      "listNode": [
        330,
        353,
        352,
        329,
        328,
        351,
        374,
        373,
        350
      ],
      "indexHead": 330
    },
    {
      "colorGecko": 0,
      "listNode": [
        372,
        371,
        394,
        395,
        418,
        419,
        420,
        443,
        442,
        465,
        466,
        489,
        490,
        513,
        514,
        515,
        538,
        537,
        536,
        559,
        560,
        583,
        584,
        561,
        562,
        585,
        586,
        563,
        540,
        539,
        516
      ],
      "indexHead": 372
    },
    {
      "colorGecko": 2,
      "listNode": [
        264,
        287,
        286
      ],
      "indexHead": 264
    },
    {
      "colorGecko": 3,
      "listNode": [
        470,
        493,
        492,
        491,
        468,
        469,
        446
      ],
      "indexHead": 470
    },
    {
      "colorGecko": 6,
      "listNode": [
        445,
        422,
        423,
        400,
        399,
        398,
        421,
        444,
        467
      ],
      "indexHead": 445
    },
    {
      "colorGecko": 4,
      "listNode": [
        397,
        396
      ],
      "indexHead": 397
    },
    {
      "colorGecko": 1,
      "listNode": [
        471,
        472,
        449
      ],
      "indexHead": 471
    },
    {
      "colorGecko": 6,
      "listNode": [
        494,
        517
      ],
      "indexHead": 494
    },
    {
      "colorGecko": 1,
      "listNode": [
        519,
        520,
        543,
        566
      ],
      "indexHead": 519
    },
    {
      "colorGecko": 6,
      "listNode": [
        497,
        474,
        475,
        498,
        499,
        522,
        521,
        544
      ],
      "indexHead": 497
    },
    {
      "colorGecko": 3,
      "listNode": [
        476,
        453,
        452
      ],
      "indexHead": 476
    },
    {
      "colorGecko": 3,
      "listNode": [
        455,
        456,
        457,
        458
      ],
      "indexHead": 455
    }
  ],
  "listBrickInMap": [],
  "listExitsInMap": [],
  "listStopInMap": [],
  "listBarrierInMap": []
}