{
  "score": 164.541809,
  "timeLimit": 0,
  "column": 34,
  "row": 44,
  "listGeckoInMap": [
    {
      "colorGecko": 3,
      "listNode": [
        140,
        174,
        173
      ],
      "indexHead": 140
    },
    {
      "colorGecko": 1,
      "listNode": [
        1434,
        1435,
        1436,
        1437
      ],
      "indexHead": 1434
    },
    {
      "colorGecko": 2,
      "listNode": [
        268,
        302
      ],
      "indexHead": 268
    },
    {
      "colorGecko": 4,
      "listNode": [
        233,
        232,
        198,
        164,
        165,
        199
      ],
      "indexHead": 233
    },
    {
      "colorGecko": 6,
      "listNode": [
        220,
        254,
        255
      ],
      "indexHead": 220
    },
    {
      "colorGecko": 4,
      "listNode": [
        289,
        323,
        357,
        391,
        392,
        393,
        359,
        358,
        324,
        290
      ],
      "indexHead": 289
    },
    {
      "colorGecko": 2,
      "listNode": [
        425,
        459
      ],
      "indexHead": 425
    },
    {
      "colorGecko": 0,
      "listNode": [
        1422,
        1421,
        1455,
        1454,
        1420
      ],
      "indexHead": 1422
    },
    {
      "colorGecko": 0,
      "listNode": [
        1260,
        1226,
        1192,
        1158,
        1124,
        1123,
        1157,
        1191,
        1225
      ],
      "indexHead": 1260
    },
    {
      "colorGecko": 3,
      "listNode": [
        1356,
        1322
      ],
      "indexHead": 1356
    },
    {
      "colorGecko": 4,
      "listNode": [
        1452,
        1453,
        1419,
        1418
      ],
      "indexHead": 1452
    },
    {
      "colorGecko": 6,
      "listNode": [
        1384,
        1350,
        1316
      ],
      "indexHead": 1384
    },
    {
      "colorGecko": 5,
      "listNode": [
        1417,
        1383,
        1382,
        1381,
        1380
      ],
      "indexHead": 1417
    },
    {
      "colorGecko": 4,
      "listNode": [
        1416,
        1415
      ],
      "indexHead": 1416
    },
    {
      "colorGecko": 6,
      "listNode": [
        1405,
        1404,
        1370
      ],
      "indexHead": 1405
    },
    {
      "colorGecko": 4,
      "listNode": [
        1160,
        1161,
        1162,
        1163,
        1197,
        1198,
        1164,
        1165
      ],
      "indexHead": 1160
    },
    {
      "colorGecko": 4,
      "listNode": [
        1166,
        1167,
        1201,
        1200,
        1199,
        1233,
        1267,
        1268,
        1302,
        1301,
        1335,
        1369,
        1403,
        1402,
        1401,
        1400,
        1366,
        1367,
        1333,
        1334,
        1368
      ],
      "indexHead": 1166
    },
    {
      "colorGecko": 0,
      "listNode": [
        1399,
        1398,
        1364,
        1365,
        1331,
        1332
      ],
      "indexHead": 1399
    },
    {
      "colorGecko": 0,
      "listNode": [
        182,
        216,
        250,
        251,
        252,
        218,
        217,
        183
      ],
      "indexHead": 182
    },
    {
      "colorGecko": 2,
      "listNode": [
        112,
        146,
        147,
        181,
        215,
        214,
        180
      ],
      "indexHead": 112
    },
    {
      "colorGecko": 4,
      "listNode": [
        249,
        283,
        317,
        351,
        385,
        384,
        383,
        349,
        315,
        281,
        247,
        248,
        282,
        316,
        350
      ],
      "indexHead": 249
    },
    {
      "colorGecko": 2,
      "listNode": [
        253,
        287,
        288,
        322,
        321
      ],
      "indexHead": 253
    },
    {
      "colorGecko": 1,
      "listNode": [
        192,
        226,
        225,
        259,
        293,
        294,
        328,
        362,
        363,
        329,
        295,
        261,
        227,
        193,
        194
      ],
      "indexHead": 192
    },
    {
      "colorGecko": 3,
      "listNode": [
        1090,
        1091,
        1092,
        1093,
        1094,
        1095,
        1096,
        1097,
        1098,
        1099,
        1065,
        1031,
        1030,
        1029,
        1028,
        1027,
        1026,
        1025,
        1024,
        1023,
        1022,
        1021,
        1055,
        1056,
        1057,
        1058,
        1059,
        1060,
        1061,
        1062,
        1063,
        1064
      ],
      "indexHead": 1090
    },
    {
      "colorGecko": 4,
      "listNode": [
        125,
        159,
        160,
        126,
        127,
        128,
        129,
        163,
        197,
        231,
        230,
        196,
        162,
        161,
        195,
        229,
        228,
        262,
        296,
        330,
        364,
        398,
        397,
        431,
        432,
        466,
        500,
        501,
        502,
        468,
        434,
        435,
        436,
        437,
        403,
        404,
        438,
        472,
        506,
        540,
        574,
        573,
        572,
        538,
        504,
        503,
        537,
        571,
        605,
        606,
        607,
        608,
        642,
        641,
        675,
        676,
        710,
        744,
        743
      ],
      "indexHead": 125
    },
    {
      "colorGecko": 1,
      "listNode": [
        402,
        401
      ],
      "indexHead": 402
    },
    {
      "colorGecko": 0,
      "listNode": [
        536,
        535,
        534,
        568,
        602
      ],
      "indexHead": 536
    },
    {
      "colorGecko": 3,
      "listNode": [
        409,
        410,
        411,
        445,
        446,
        412,
        413,
        447,
        448,
        414,
        415,
        449,
        450,
        484,
        518,
        517,
        516,
        515,
        514,
        513,
        512,
        478,
        444,
        443,
        477
      ],
      "indexHead": 409
    },
    {
      "colorGecko": 1,
      "listNode": [
        341,
        307
      ],
      "indexHead": 341
    },
    {
      "colorGecko": 4,
      "listNode": [
        519,
        520,
        554,
        553
      ],
      "indexHead": 519
    },
    {
      "colorGecko": 6,
      "listNode": [
        206,
        207,
        208,
        209,
        210,
        176,
        175,
        141,
        107,
        108,
        109,
        110,
        111,
        145,
        179,
        213,
        212,
        246,
        280,
        314,
        348,
        347,
        346,
        380,
        381,
        382,
        416,
        417,
        418,
        419,
        453,
        452,
        451,
        485,
        486,
        487,
        488,
        489,
        523,
        524,
        558,
        557,
        591,
        592,
        593,
        627,
        628,
        594,
        595,
        596,
        597,
        598,
        599
      ],
      "indexHead": 206
    },
    {
      "colorGecko": 5,
      "listNode": [
        240,
        274
      ],
      "indexHead": 240
    },
    {
      "colorGecko": 4,
      "listNode": [
        142,
        143,
        144
      ],
      "indexHead": 142
    },
    {
      "colorGecko": 4,
      "listNode": [
        178,
        177,
        211
      ],
      "indexHead": 178
    },
    {
      "colorGecko": 4,
      "listNode": [
        241,
        275,
        276,
        310,
        344,
        378,
        379,
        345,
        311,
        277,
        278,
        279,
        245,
        244,
        243,
        242
      ],
      "indexHead": 241
    },
    {
      "colorGecko": 6,
      "listNode": [
        256,
        257,
        291,
        325,
        326,
        327,
        361,
        395,
        394,
        428,
        462,
        461,
        427,
        426,
        460,
        494,
        493,
        527,
        526,
        492,
        491
      ],
      "indexHead": 256
    },
    {
      "colorGecko": 6,
      "listNode": [
        528,
        562,
        561
      ],
      "indexHead": 528
    },
    {
      "colorGecko": 5,
      "listNode": [
        664,
        698,
        699,
        665,
        631
      ],
      "indexHead": 664
    },
    {
      "colorGecko": 6,
      "listNode": [
        1371,
        1372,
        1373,
        1374,
        1375
      ],
      "indexHead": 1371
    },
    {
      "colorGecko": 3,
      "listNode": [
        1385,
        1386,
        1387,
        1388,
        1389,
        1355,
        1321,
        1287,
        1288,
        1289,
        1255,
        1221,
        1187,
        1153,
        1119,
        1085,
        1051,
        1050,
        1049,
        1048,
        1047,
        1046,
        1045,
        1044,
        1043,
        1042,
        1041,
        1040,
        1006,
        972,
        938,
        904,
        870,
        871,
        872,
        873,
        874,
        875,
        876,
        877,
        878,
        879,
        845,
        811,
        777,
        776,
        775,
        774,
        773,
        807
      ],
      "indexHead": 1385
    },
    {
      "colorGecko": 5,
      "listNode": [
        1254,
        1253
      ],
      "indexHead": 1254
    },
    {
      "colorGecko": 6,
      "listNode": [
        1186,
        1152,
        1118,
        1084
      ],
      "indexHead": 1186
    },
    {
      "colorGecko": 0,
      "listNode": [
        1354,
        1353,
        1352
      ],
      "indexHead": 1354
    },
    {
      "colorGecko": 0,
      "listNode": [
        1351,
        1317,
        1318,
        1319,
        1285,
        1286,
        1252,
        1251,
        1250,
        1284,
        1283,
        1282,
        1281,
        1315,
        1349,
        1348,
        1347,
        1313,
        1279,
        1245,
        1246,
        1247,
        1213,
        1212,
        1211,
        1210,
        1244,
        1278,
        1277,
        1311,
        1345,
        1346,
        1312
      ],
      "indexHead": 1351
    },
    {
      "colorGecko": 2,
      "listNode": [
        1314,
        1280
      ],
      "indexHead": 1314
    },
    {
      "colorGecko": 3,
      "listNode": [
        629,
        663,
        697,
        731,
        732,
        733,
        734,
        735,
        736,
        702,
        668,
        669,
        703,
        704,
        705,
        739,
        738,
        772,
        806,
        805,
        804,
        770,
        769,
        768,
        802,
        836,
        835,
        801,
        767,
        766,
        800,
        799
      ],
      "indexHead": 629
    },
    {
      "colorGecko": 4,
      "listNode": [
        834,
        868,
        902,
        936,
        970,
        1004,
        1038,
        1039,
        1073,
        1074,
        1075,
        1076,
        1110,
        1111,
        1112,
        1146,
        1180,
        1214,
        1248,
        1249
      ],
      "indexHead": 834
    },
    {
      "colorGecko": 2,
      "listNode": [
        1072,
        1106,
        1140,
        1174,
        1175,
        1209,
        1243,
        1242,
        1241,
        1207,
        1206,
        1172,
        1173,
        1139,
        1105,
        1071,
        1037,
        1036,
        1035,
        1034,
        1000,
        999,
        965,
        964,
        963,
        997,
        998,
        1032,
        1033,
        1067,
        1101,
        1100,
        1134,
        1168,
        1202,
        1236,
        1270,
        1271,
        1272,
        1273,
        1274,
        1308,
        1309,
        1343,
        1344
      ],
      "indexHead": 1072
    },
    {
      "colorGecko": 2,
      "listNode": [
        1342,
        1341,
        1340,
        1339,
        1338,
        1337,
        1336
      ],
      "indexHead": 1342
    },
    {
      "colorGecko": 6,
      "listNode": [
        1240,
        1239,
        1205,
        1171,
        1137,
        1138,
        1104,
        1070,
        1069,
        1103,
        1102,
        1136,
        1135,
        1169,
        1170,
        1204,
        1238,
        1237,
        1203
      ],
      "indexHead": 1240
    },
    {
      "colorGecko": 1,
      "listNode": [
        1330,
        1329,
        1295,
        1296,
        1262,
        1263,
        1264,
        1265,
        1231,
        1232,
        1266,
        1300,
        1299,
        1298,
        1297
      ],
      "indexHead": 1330
    },
    {
      "colorGecko": 0,
      "listNode": [
        1230,
        1196,
        1195,
        1229,
        1228,
        1194,
        1193,
        1227,
        1261
      ],
      "indexHead": 1230
    },
    {
      "colorGecko": 5,
      "listNode": [
        1216,
        1217,
        1183,
        1149,
        1148,
        1182,
        1181,
        1147,
        1113,
        1079,
        1080,
        1081,
        1082,
        1083,
        1117,
        1151,
        1150,
        1184,
        1185,
        1219,
        1218
      ],
      "indexHead": 1216
    },
    {
      "colorGecko": 1,
      "listNode": [
        1115,
        1114
      ],
      "indexHead": 1115
    },
    {
      "colorGecko": 6,
      "listNode": [
        1144,
        1143,
        1177,
        1178,
        1179
      ],
      "indexHead": 1144
    },
    {
      "colorGecko": 5,
      "listNode": [
        978,
        944,
        910,
        909,
        908,
        907,
        906,
        940,
        974,
        975,
        1009,
        1010,
        976,
        942,
        943,
        977,
        1011
      ],
      "indexHead": 978
    },
    {
      "colorGecko": 6,
      "listNode": [
        1235,
        1234
      ],
      "indexHead": 1235
    },
    {
      "colorGecko": 2,
      "listNode": [
        1013,
        979,
        945,
        911,
        912,
        913,
        947,
        946
      ],
      "indexHead": 1013
    },
    {
      "colorGecko": 1,
      "listNode": [
        843,
        809,
        808,
        842,
        841
      ],
      "indexHead": 843
    },
    {
      "colorGecko": 6,
      "listNode": [
        741,
        707,
        673,
        639,
        638,
        672,
        671,
        670,
        636,
        635,
        634,
        633,
        632,
        666,
        700,
        701,
        667
      ],
      "indexHead": 741
    },
    {
      "colorGecko": 4,
      "listNode": [
        1077,
        1078
      ],
      "indexHead": 1077
    },
    {
      "colorGecko": 5,
      "listNode": [
        740,
        706
      ],
      "indexHead": 740
    },
    {
      "colorGecko": 4,
      "listNode": [
        604,
        570
      ],
      "indexHead": 604
    },
    {
      "colorGecko": 1,
      "listNode": [
        400,
        366,
        367,
        368,
        369,
        370,
        336,
        335
      ],
      "indexHead": 400
    },
    {
      "colorGecko": 5,
      "listNode": [
        334,
        333,
        299,
        300,
        301,
        267,
        266,
        265
      ],
      "indexHead": 334
    },
    {
      "colorGecko": 5,
      "listNode": [
        332,
        331,
        365,
        399,
        433,
        467
      ],
      "indexHead": 332
    },
    {
      "colorGecko": 3,
      "listNode": [
        298,
        264,
        263,
        297
      ],
      "indexHead": 298
    },
    {
      "colorGecko": 0,
      "listNode": [
        569,
        603,
        637
      ],
      "indexHead": 569
    },
    {
      "colorGecko": 3,
      "listNode": [
        601,
        600,
        566,
        532,
        533,
        499,
        465,
        464,
        430,
        429,
        463,
        497,
        531,
        565
      ],
      "indexHead": 601
    },
    {
      "colorGecko": 1,
      "listNode": [
        626,
        625,
        659
      ],
      "indexHead": 626
    },
    {
      "colorGecko": 5,
      "listNode": [
        471,
        505
      ],
      "indexHead": 471
    },
    {
      "colorGecko": 0,
      "listNode": [
        470,
        469
      ],
      "indexHead": 470
    },
    {
      "colorGecko": 6,
      "listNode": [
        981,
        1015,
        1016,
        982,
        948,
        914,
        880,
        846,
        812,
        778
      ],
      "indexHead": 981
    },
    {
      "colorGecko": 1,
      "listNode": [
        496,
        495,
        529,
        563,
        564,
        530
      ],
      "indexHead": 496
    },
    {
      "colorGecko": 0,
      "listNode": [
        560,
        559,
        525
      ],
      "indexHead": 560
    },
    {
      "colorGecko": 2,
      "listNode": [
        556,
        555,
        589,
        588,
        587,
        586,
        552,
        551,
        585,
        584,
        550,
        549,
        548,
        547,
        546
      ],
      "indexHead": 556
    },
    {
      "colorGecko": 4,
      "listNode": [
        522,
        521
      ],
      "indexHead": 522
    },
    {
      "colorGecko": 0,
      "listNode": [
        674,
        708,
        742
      ],
      "indexHead": 674
    },
    {
      "colorGecko": 3,
      "listNode": [
        662,
        661,
        695,
        696
      ],
      "indexHead": 662
    },
    {
      "colorGecko": 0,
      "listNode": [
        810,
        844
      ],
      "indexHead": 810
    },
    {
      "colorGecko": 1,
      "listNode": [
        980,
        1014
      ],
      "indexHead": 980
    },
    {
      "colorGecko": 2,
      "listNode": [
        840,
        839,
        838,
        837,
        803
      ],
      "indexHead": 840
    },
    {
      "colorGecko": 4,
      "listNode": [
        482,
        481,
        480,
        479
      ],
      "indexHead": 482
    },
    {
      "colorGecko": 2,
      "listNode": [
        869,
        903,
        937,
        971,
        1005
      ],
      "indexHead": 869
    },
    {
      "colorGecko": 4,
      "listNode": [
        1107,
        1141,
        1142,
        1108,
        1109
      ],
      "indexHead": 1107
    },
    {
      "colorGecko": 4,
      "listNode": [
        1133,
        1132,
        1131,
        1130,
        1129,
        1128,
        1127,
        1126,
        1125
      ],
      "indexHead": 1133
    },
    {
      "colorGecko": 0,
      "listNode": [
        292,
        258,
        224
      ],
      "indexHead": 292
    },
    {
      "colorGecko": 4,
      "listNode": [
        286,
        285,
        284
      ],
      "indexHead": 286
    },
    {
      "colorGecko": 1,
      "listNode": [
        996,
        962,
        961,
        995,
        994
      ],
      "indexHead": 996
    },
    {
      "colorGecko": 3,
      "listNode": [
        927,
        893,
        894,
        928,
        929
      ],
      "indexHead": 927
    },
    {
      "colorGecko": 5,
      "listNode": [
        960,
        926,
        925,
        891,
        857,
        823,
        789,
        788,
        787,
        753,
        719,
        718,
        717,
        751,
        752,
        786,
        785,
        819,
        820,
        821,
        822,
        856,
        890,
        924,
        923,
        922,
        921,
        955,
        989,
        990,
        956,
        957,
        958,
        959,
        993,
        992,
        991
      ],
      "indexHead": 960
    },
    {
      "colorGecko": 3,
      "listNode": [
        887,
        853,
        854,
        888,
        889,
        855
      ],
      "indexHead": 887
    },
    {
      "colorGecko": 0,
      "listNode": [
        683,
        649
      ],
      "indexHead": 683
    },
    {
      "colorGecko": 4,
      "listNode": [
        684,
        685,
        686,
        687,
        688,
        654,
        620,
        619,
        653,
        652,
        618,
        617,
        583,
        582,
        581,
        615,
        616,
        650,
        651
      ],
      "indexHead": 684
    },
    {
      "colorGecko": 6,
      "listNode": [
        655,
        656,
        657,
        623,
        622,
        621
      ],
      "indexHead": 655
    },
    {
      "colorGecko": 3,
      "listNode": [
        859,
        825,
        791,
        757,
        758,
        759,
        725,
        724,
        723,
        722,
        721,
        720,
        754,
        755,
        756,
        790,
        824,
        858,
        892
      ],
      "indexHead": 859
    },
    {
      "colorGecko": 4,
      "listNode": [
        860,
        861,
        862,
        828,
        794,
        760,
        726,
        692,
        658,
        624,
        590
      ],
      "indexHead": 860
    },
    {
      "colorGecko": 3,
      "listNode": [
        826,
        827,
        793,
        792
      ],
      "indexHead": 826
    },
    {
      "colorGecko": 0,
      "listNode": [
        895,
        896,
        930,
        931
      ],
      "indexHead": 895
    },
    {
      "colorGecko": 6,
      "listNode": [
        1269,
        1303,
        1304,
        1305,
        1306,
        1307
      ],
      "indexHead": 1269
    },
    {
      "colorGecko": 3,
      "listNode": [
        454,
        420,
        386,
        352,
        318,
        319,
        320,
        354,
        353,
        387,
        421,
        455,
        456,
        457,
        458,
        424,
        390,
        356,
        355,
        389,
        388,
        422,
        423
      ],
      "indexHead": 454
    },
    {
      "colorGecko": 1,
      "listNode": [
        1275,
        1276,
        1310
      ],
      "indexHead": 1275
    },
    {
      "colorGecko": 3,
      "listNode": [
        1003,
        969,
        935,
        934
      ],
      "indexHead": 1003
    },
    {
      "colorGecko": 1,
      "listNode": [
        693,
        727,
        761,
        795,
        829,
        863,
        897,
        898,
        899,
        900,
        901,
        867,
        833,
        832,
        798,
        764,
        730,
        729,
        728,
        694,
        660
      ],
      "indexHead": 693
    },
    {
      "colorGecko": 3,
      "listNode": [
        796,
        797,
        831,
        830
      ],
      "indexHead": 796
    },
    {
      "colorGecko": 4,
      "listNode": [
        864,
        865,
        866
      ],
      "indexHead": 864
    },
    {
      "colorGecko": 4,
      "listNode": [
        313,
        312
      ],
      "indexHead": 313
    },
    {
      "colorGecko": 4,
      "listNode": [
        309,
        308,
        342,
        376,
        377,
        343
      ],
      "indexHead": 309
    },
    {
      "colorGecko": 6,
      "listNode": [
        920,
        954,
        988
      ],
      "indexHead": 920
    },
    {
      "colorGecko": 5,
      "listNode": [
        1008,
        1007
      ],
      "indexHead": 1008
    },
    {
      "colorGecko": 4,
      "listNode": [
        973,
        939,
        905
      ],
      "indexHead": 973
    },
    {
      "colorGecko": 3,
      "listNode": [
        933,
        932,
        966,
        967,
        968,
        1002,
        1001
      ],
      "indexHead": 933
    },
    {
      "colorGecko": 1,
      "listNode": [
        771,
        737
      ],
      "indexHead": 771
    },
    {
      "colorGecko": 1,
      "listNode": [
        690,
        689
      ],
      "indexHead": 690
    },
    {
      "colorGecko": 1,
      "listNode": [
        763,
        762
      ],
      "indexHead": 763
    }
  ],
  "listBrickInMap": [],
  "listExitsInMap": [],
  "listStopInMap": [],
  "listBarrierInMap": []
}